gdal2numpy/__init__.py
gdal2numpy/filesystem.py
gdal2numpy/gdal_merge.py
gdal2numpy/gdal_translate.py
gdal2numpy/gdalwarp.py
gdal2numpy/module_GDAL2Numpy.py
gdal2numpy/module_Numpy2GTiff.py
gdal2numpy/module_esri_shape.py
gdal2numpy/module_extrusion.py
gdal2numpy/module_features.py
gdal2numpy/module_gdal.py
gdal2numpy/module_geojson.py
gdal2numpy/module_geolocate.py
gdal2numpy/module_http.py
gdal2numpy/module_log.py
gdal2numpy/module_memory.py
gdal2numpy/module_meta.py
gdal2numpy/module_ogr.py
gdal2numpy/module_open.py
gdal2numpy/module_s3.py
gdal2numpy/module_types.py
gdal2numpy/module_xml.py
gdal2numpy/rasterizelike.py
gdal2numpy/rasterlike.py
gdal2numpy/data/pe_hash_list.json
gdal2numpy/data/spatial_ref_sys_all.json
gdal2numpy-0.0.411.dist-info/LICENSE
gdal2numpy-0.0.411.dist-info/METADATA
gdal2numpy-0.0.411.dist-info/WHEEL
gdal2numpy-0.0.411.dist-info/top_level.txt
gdal2numpy-0.0.411.dist-info/RECORD
