Metadata-Version: 2.1
Name: gdal2numpy
Version: 0.0.411
Summary: An utils functions package
Home-page: https://github.com/SaferPlaces2023/gdal2numpy.git
Author: Valerio Luzzi, Marco Renzi
Author-email: valerio.luzzi@gecosistema.com, marco.renzi@gecosistema.com
License: MIT
Classifier: Programming Language :: Python :: 3
Classifier: License :: OSI Approved :: MIT License
Classifier: Operating System :: OS Independent
License-File: LICENSE
Requires-Dist: setuptools
Requires-Dist: psutil
Requires-Dist: requests
Requires-Dist: gdal
Requires-Dist: numpy
Requires-Dist: boto3
Requires-Dist: pyproj
Requires-Dist: levenshtein
Requires-Dist: xmltodict
